{
  "@context": "https://isoics.org/ics/ns/subgroup.jsonld",
  "code": "29.240.01",
  "description": "Power transmission and distribution networks in general",
  "descriptionFull": "Electrical engineering. Power transmission and distribution networks. Power transmission and distribution networks in general.",
  "fieldcode": "29",
  "groupcode": "240",
  "notes": [
    {
      "ics-code": "33.040.60",
      "text": "Powerline telecommunications, see {ics-code}"
    }
  ],
  "subgroupcode": "01"
}
